{"type":"Image","props":{"y":0,"x":0,"width":720,"scaleY":1,"scaleX":1,"presetID":1,"name":"GuidanceDialog","isPresetRoot":true,"height":1280},"compId":403,"child":[{"type":"Script","props":{"ske":"@node:408","presetID":2,"runtime":"core/component/GuidanceDialog.ts"},"compId":404},{"type":"Sprite","props":{"presetID":3,"name":"bg"},"compId":405},{"type":"SkeletonPlayer","props":{"y":0,"x":0,"url":"lobby/guid/circle02.sk","presetID":5,"name":"ske","runtime":"Laya.Skeleton"},"compId":408},{"type":"Image","props":{"y":100,"x":0,"skin":"lobby/guid/ic_jiantou.png","scaleY":1,"presetID":6,"name":"jt","anchorY":0.5,"anchorX":0.5},"compId":410}],"loadList":["lobby/guid/circle02.sk","lobby/guid/ic_jiantou.png"],"loadList3D":[]}